xbp/__init__.py
xbp/__main__.py
xbp/builder.py
xbp/parser.py
xbp-1.2.dist-info/LICENSE
xbp-1.2.dist-info/METADATA
xbp-1.2.dist-info/WHEEL
xbp-1.2.dist-info/entry_points.txt
xbp-1.2.dist-info/top_level.txt
xbp-1.2.dist-info/RECORD
