Metadata-Version: 2.1
Name: xbp
Version: 1.2
Summary: Fast C/C++ Builder written in Python
Home-page: https://github.com/bomkei/BuildPy
Author: bomkei
Author-email: bunkeiprogrammer@gmail.com
License: MIT
Platform: UNKNOWN
